fastmeteo/__init__.py
fastmeteo/cli/__init__.py
fastmeteo/cli/sync.py
fastmeteo/core/__init__.py
fastmeteo/core/grid.py
fastmeteo/network/__init__.py
fastmeteo/network/client.py
fastmeteo/network/server.py
fastmeteo/source/__init__.py
fastmeteo/source/arco_era5.py
fastmeteo/source/arpege.py
fastmeteo/source/level_137.csv
fastmeteo-1.1.0.dist-info/METADATA
fastmeteo-1.1.0.dist-info/WHEEL
fastmeteo-1.1.0.dist-info/entry_points.txt
fastmeteo-1.1.0.dist-info/licenses/LICENSE
fastmeteo-1.1.0.dist-info/RECORD
