Metadata-Version: 2.4
Name: fastmeteo
Version: 1.1.0
Summary: A fast Python tool for regridding and interpolating meteorological data
Project-URL: homepage, https://github.com/open-aviation/fastmeteo
Project-URL: repository, https://github.com/open-aviation/fastmeteo
Project-URL: issues, https://github.com/open-aviation/fastmeteo/issues
Author-email: Junzi Sun <git@junzis.com>, Xavier Olive <git@xoolive.org>
License: GNU LGPL v3
License-File: LICENSE
Classifier: Development Status :: 4 - Beta
Classifier: Intended Audience :: Developers
Classifier: License :: OSI Approved :: GNU Lesser General Public License v3 (LGPLv3)
Classifier: Programming Language :: Python :: 3
Classifier: Topic :: Software Development :: Libraries :: Python Modules
Requires-Python: >=3.11
Requires-Dist: cfgrib>=0.9.15.0
Requires-Dist: click>=8.1.8
Requires-Dist: dask>=2025.3.0
Requires-Dist: fastapi>=0.115.12
Requires-Dist: fsspec>=2025.3.2
Requires-Dist: gcsfs>=2025.3.2
Requires-Dist: httpx>=0.28.1
Requires-Dist: impunity>=1.0.5
Requires-Dist: netcdf4>=1.7.2
Requires-Dist: numpy>=2.2.4
Requires-Dist: pandas>=2.2.3
Requires-Dist: pitot>=0.3.2
Requires-Dist: scipy>=1.15.2
Requires-Dist: tqdm>=4.67.1
Requires-Dist: uvicorn>=0.34.1
Requires-Dist: xarray>=2025.3.1
Requires-Dist: zarr<3.0.0,>=2.18.2
